{
  "uid": {
    "__TYPE__": "UIDContent",
    "value": "fall"
  },
  "title": {
    "__TYPE__": "StructuredTextContent",
    "value": [
      {
        "type": "heading1",
        "content": {
          "text": "Fierce"
        }
      }
    ]
  },
  "publishDate": {
    "__TYPE__": "FieldContent",
    "type": "Date",
    "value": "2022-05-26"
  },
  "featuredImage": {
    "__TYPE__": "ImageContent",
    "origin": {
      "id": "main",
      "url": "https://images.unsplash.com/photo-1587653915936-5623ea0b949a",
      "width": 4000,
      "height": 4000
    },
    "url": "https://images.unsplash.com/photo-1587653915936-5623ea0b949a?rect=0%2C500%2C4000%2C3000&w=2000&h=1500",
    "width": 2000,
    "height": 1500,
    "edit": {
      "zoom": 1,
      "crop": {
        "x": 0,
        "y": 500
      },
      "background": "transparent"
    },
    "thumbnails": {}
  },
  "slices": {
    "__TYPE__": "SliceContentType",
    "value": [
      {
        "key": "image$9ad4faf3-5a8a-4cc2-931d-8912e8e3bcc0",
        "name": "image",
        "widget": {
          "__TYPE__": "SharedSliceContent",
          "variation": "default",
          "primary": {
            "image": {
              "__TYPE__": "ImageContent",
              "origin": {
                "id": "main",
                "url": "https://images.unsplash.com/photo-1560762484-813fc97650a0",
                "width": 3344,
                "height": 2509
              },
              "url": "https://images.unsplash.com/photo-1560762484-813fc97650a0",
              "width": 3344,
              "height": 2509,
              "edit": {
                "zoom": 1,
                "crop": {
                  "x": 0,
                  "y": 0
                },
                "background": "transparent"
              },
              "thumbnails": {}
            },
            "caption": {
              "__TYPE__": "StructuredTextContent",
              "value": [
                {
                  "type": "paragraph",
                  "content": {
                    "text": "Voluptate enim laboris sit incididunt id labore."
                  }
                }
              ]
            }
          },
          "items": [
            {
              "__TYPE__": "GroupItemContent",
              "value": []
            }
          ]
        }
      },
      {
        "key": "quote$97535d7a-99af-48f1-9e50-a3fa604f4c3b",
        "name": "quote",
        "widget": {
          "__TYPE__": "SharedSliceContent",
          "variation": "default",
          "primary": {
            "quote": {
              "__TYPE__": "StructuredTextContent",
              "value": [
                {
                  "type": "heading2",
                  "content": {
                    "text": "Complex"
                  }
                }
              ]
            },
            "source": {
              "__TYPE__": "FieldContent",
              "value": "pot",
              "type": "Text"
            }
          },
          "items": [
            {
              "__TYPE__": "GroupItemContent",
              "value": []
            }
          ]
        }
      },
      {
        "key": "text$3972da98-35aa-4082-9afb-d0f0f7dcde6a",
        "name": "text",
        "widget": {
          "__TYPE__": "SharedSliceContent",
          "variation": "default",
          "primary": {
            "text": {
              "__TYPE__": "StructuredTextContent",
              "value": [
                {
                  "type": "paragraph",
                  "content": {
                    "text": "Et dolor cupidatat consectetur cupidatat culpa exercitation cupidatat. Occaecat exercitation ea magna cillum mollit aliquip voluptate aliqua culpa. Labore aliqua consequat excepteur ex consequat ipsum nulla."
                  }
                }
              ]
            }
          },
          "items": [
            {
              "__TYPE__": "GroupItemContent",
              "value": []
            }
          ]
        }
      },
      {
        "key": "contact_form$341684d2-989a-4e0b-b264-00158176def7",
        "name": "contact_form",
        "widget": {
          "__TYPE__": "SharedSliceContent",
          "variation": "default",
          "primary": {},
          "items": [
            {
              "__TYPE__": "GroupItemContent",
              "value": []
            }
          ]
        }
      }
    ]
  }
}